wagtail_hallo/__init__.py
wagtail_hallo/apps.py
wagtail_hallo/hallo.py
wagtail_hallo/plugins.py
wagtail_hallo/wagtail_hooks.py
wagtail_hallo/migrations/__init__.py
wagtail_hallo/static/css/hallo.css
wagtail_hallo/static/css/icons.css
wagtail_hallo/static/fonts/wagtail.woff
wagtail_hallo/static/js/hallo-editor.js
wagtail_hallo/static/js/hallo-telepath.js
wagtail_hallo/static/js/hallo-plugins/hallo-hr.js
wagtail_hallo/static/js/hallo-plugins/hallo-requireparagraphs.js
wagtail_hallo/static/js/hallo-plugins/hallo-wagtaildoclink.js
wagtail_hallo/static/js/hallo-plugins/hallo-wagtailembeds.js
wagtail_hallo/static/js/hallo-plugins/hallo-wagtailimage.js
wagtail_hallo/static/js/hallo-plugins/hallo-wagtaillink.js
wagtail_hallo/static/js/vendor/hallo.js
wagtail_hallo/templates/wagtail_hallo/widgets/hallo_rich_text_area.html
wagtail_hallo/test/__init__.py
wagtail_hallo/test/apps.py
wagtail_hallo/test/models.py
wagtail_hallo/test/settings.py
wagtail_hallo/test/urls.py
wagtail_hallo/test/wagtail_hooks.py
wagtail_hallo/test/fixtures/test.json
wagtail_hallo/test/migrations/0001_initial.py
wagtail_hallo/test/migrations/0002_richtextfieldwithfeaturespage.py
wagtail_hallo/test/migrations/__init__.py
wagtail_hallo/test/testapp/templates/hallo_test_page.html
wagtail_hallo/test/tests/__init__.py
wagtail_hallo/test/tests/hallo.test.js
wagtail_hallo/test/tests/test_dbwhitelister.py
wagtail_hallo/test/tests/test_hallo.py
wagtail_hallo/test/tests/test_hallo_plugins.py
wagtail_hallo/test/tests/utils.py
wagtail_hallo-0.6.0.dist-info/LICENSE
wagtail_hallo-0.6.0.dist-info/METADATA
wagtail_hallo-0.6.0.dist-info/WHEEL
wagtail_hallo-0.6.0.dist-info/top_level.txt
wagtail_hallo-0.6.0.dist-info/RECORD
