Metadata-Version: 2.1
Name: wagtail-hallo
Version: 0.6.0
Summary: Wagtail Hallo - The legacy richtext editor for Wagtail.
Home-page: https://github.com/wagtail-nest/wagtail-hallo
Author: Wagtail core team
Author-email: hello@wagtail.org
License: MIT
Classifier: Development Status :: 5 - Production/Stable
Classifier: Intended Audience :: Developers
Classifier: License :: OSI Approved :: MIT License
Classifier: Operating System :: OS Independent
Classifier: Programming Language :: Python
Classifier: Programming Language :: Python :: 3
Classifier: Programming Language :: Python :: 3.9
Classifier: Programming Language :: Python :: 3.10
Classifier: Programming Language :: Python :: 3.11
Classifier: Programming Language :: Python :: 3.12
Classifier: Framework :: Django
Classifier: Framework :: Django :: 4.2
Classifier: Framework :: Django :: 5.0
Classifier: Framework :: Wagtail
Classifier: Framework :: Wagtail :: 4
Classifier: Framework :: Wagtail :: 5
Classifier: Framework :: Wagtail :: 6
License-File: LICENSE
Requires-Dist: Django<6.0,>=4.2
Requires-Dist: Wagtail<7.0,>=4.0
Provides-Extra: testing
Requires-Dist: html5lib==1.1; extra == "testing"
